{
 "custom_fields": [
  {
   "_assign": null,
   "_comments": null,
   "_liked_by": null,
   "_user_tags": null,
   "allow_on_submit": 0,
   "bold": 0,
   "collapsible": 0,
   "collapsible_depends_on": null,
   "columns": 0,
   "creation": "2019-09-13 16:28:13.305301",
   "default": null,
   "depends_on": null,
   "description": null,
   "docstatus": 0,
   "dt": "Delivery Note",
   "fetch_from": null,
   "fetch_if_empty": 0,
   "fieldname": "creator",
   "fieldtype": "Data",
   "hidden": 0,
   "idx": 5,
   "ignore_user_permissions": 0,
   "ignore_xss_filter": 0,
   "in_global_search": 0,
   "in_list_view": 0,
   "in_standard_filter": 0,
   "insert_after": "naming_series",
   "label": "Creator",
   "modified": "2019-09-13 16:28:13.305301",
   "modified_by": "Administrator",
   "name": "Delivery Note-creator",
   "no_copy": 0,
   "options": null,
   "owner": "Administrator",
   "parent": null,
   "parentfield": null,
   "parenttype": null,
   "permlevel": 0,
   "precision": "",
   "print_hide": 0,
   "print_hide_if_no_value": 0,
   "print_width": null,
   "read_only": 1,
   "report_hide": 0,
   "reqd": 0,
   "search_index": 0,
   "translatable": 0,
   "unique": 0,
   "width": null
  },
  {
   "_assign": null,
   "_comments": null,
   "_liked_by": null,
   "_user_tags": null,
   "allow_on_submit": 0,
   "bold": 0,
   "collapsible": 0,
   "collapsible_depends_on": null,
   "columns": 0,
   "creation": "2019-08-24 20:17:36.067774",
   "default": null,
   "depends_on": null,
   "description": null,
   "docstatus": 0,
   "dt": "Delivery Note",
   "fetch_from": null,
   "fetch_if_empty": 0,
   "fieldname": "bc_date",
   "fieldtype": "Date",
   "hidden": 0,
   "idx": 23,
   "ignore_user_permissions": 0,
   "ignore_xss_filter": 0,
   "in_global_search": 0,
   "in_list_view": 0,
   "in_standard_filter": 0,
   "insert_after": "bc_number",
   "label": "BC Date",
   "modified": "2019-08-24 20:17:36.067774",
   "modified_by": "Administrator",
   "name": "Delivery Note-bc_date",
   "no_copy": 0,
   "options": null,
   "owner": "Administrator",
   "parent": null,
   "parentfield": null,
   "parenttype": null,
   "permlevel": 0,
   "precision": "",
   "print_hide": 0,
   "print_hide_if_no_value": 0,
   "print_width": null,
   "read_only": 0,
   "report_hide": 0,
   "reqd": 1,
   "search_index": 0,
   "translatable": 0,
   "unique": 0,
   "width": null
  },
  {
   "_assign": null,
   "_comments": null,
   "_liked_by": null,
   "_user_tags": null,
   "allow_on_submit": 0,
   "bold": 0,
   "collapsible": 0,
   "collapsible_depends_on": null,
   "columns": 0,
   "creation": "2019-08-24 20:17:35.652281",
   "default": null,
   "depends_on": null,
   "description": null,
   "docstatus": 0,
   "dt": "Delivery Note",
   "fetch_from": null,
   "fetch_if_empty": 0,
   "fieldname": "bc_number",
   "fieldtype": "Data",
   "hidden": 0,
   "idx": 22,
   "ignore_user_permissions": 0,
   "ignore_xss_filter": 0,
   "in_global_search": 0,
   "in_list_view": 0,
   "in_standard_filter": 0,
   "insert_after": "bc_type",
   "label": "BC Number",
   "modified": "2019-08-24 20:17:35.652281",
   "modified_by": "Administrator",
   "name": "Delivery Note-bc_number",
   "no_copy": 0,
   "options": null,
   "owner": "Administrator",
   "parent": null,
   "parentfield": null,
   "parenttype": null,
   "permlevel": 0,
   "precision": "",
   "print_hide": 0,
   "print_hide_if_no_value": 0,
   "print_width": null,
   "read_only": 0,
   "report_hide": 0,
   "reqd": 1,
   "search_index": 0,
   "translatable": 1,
   "unique": 0,
   "width": null
  },
  {
   "_assign": null,
   "_comments": null,
   "_liked_by": null,
   "_user_tags": null,
   "allow_on_submit": 0,
   "bold": 0,
   "collapsible": 0,
   "collapsible_depends_on": null,
   "columns": 0,
   "creation": "2019-08-24 20:17:01.153648",
   "default": null,
   "depends_on": null,
   "description": null,
   "docstatus": 0,
   "dt": "Delivery Note",
   "fetch_from": null,
   "fetch_if_empty": 0,
   "fieldname": "bc_type",
   "fieldtype": "Select",
   "hidden": 0,
   "idx": 21,
   "ignore_user_permissions": 0,
   "ignore_xss_filter": 0,
   "in_global_search": 0,
   "in_list_view": 0,
   "in_standard_filter": 0,
   "insert_after": "section_break_19",
   "label": "BC Type",
   "modified": "2019-08-24 20:17:01.153648",
   "modified_by": "Administrator",
   "name": "Delivery Note-bc_type",
   "no_copy": 0,
   "options": "\nBC 2.7\nBC 3.0\nBC 4.1\nBC 2.6.1",
   "owner": "Administrator",
   "parent": null,
   "parentfield": null,
   "parenttype": null,
   "permlevel": 0,
   "precision": "",
   "print_hide": 0,
   "print_hide_if_no_value": 0,
   "print_width": null,
   "read_only": 0,
   "report_hide": 0,
   "reqd": 1,
   "search_index": 0,
   "translatable": 1,
   "unique": 0,
   "width": null
  },
  {
   "_assign": null,
   "_comments": null,
   "_liked_by": null,
   "_user_tags": null,
   "allow_on_submit": 0,
   "bold": 0,
   "collapsible": 0,
   "collapsible_depends_on": null,
   "columns": 0,
   "creation": "2019-08-21 09:04:13.868374",
   "default": null,
   "depends_on": null,
   "description": null,
   "docstatus": 0,
   "dt": "Delivery Note",
   "fetch_from": null,
   "fetch_if_empty": 0,
   "fieldname": "section_break_19",
   "fieldtype": "Section Break",
   "hidden": 0,
   "idx": 20,
   "ignore_user_permissions": 0,
   "ignore_xss_filter": 0,
   "in_global_search": 0,
   "in_list_view": 0,
   "in_standard_filter": 0,
   "insert_after": "po_no",
   "label": "Customs Document",
   "modified": "2019-08-21 09:04:13.868374",
   "modified_by": "Administrator",
   "name": "Delivery Note-section_break_19",
   "no_copy": 0,
   "options": null,
   "owner": "Administrator",
   "parent": null,
   "parentfield": null,
   "parenttype": null,
   "permlevel": 0,
   "precision": "",
   "print_hide": 0,
   "print_hide_if_no_value": 0,
   "print_width": null,
   "read_only": 0,
   "report_hide": 0,
   "reqd": 0,
   "search_index": 0,
   "translatable": 0,
   "unique": 0,
   "width": null
  },
  {
   "_assign": null,
   "_comments": null,
   "_liked_by": null,
   "_user_tags": null,
   "allow_on_submit": 0,
   "bold": 0,
   "collapsible": 0,
   "collapsible_depends_on": null,
   "columns": 0,
   "creation": "2019-08-17 22:18:15.119926",
   "default": null,
   "depends_on": null,
   "description": null,
   "docstatus": 0,
   "dt": "Delivery Note",
   "fetch_from": null,
   "fetch_if_empty": 0,
   "fieldname": "exchange_rate_idr",
   "fieldtype": "Data",
   "hidden": 0,
   "idx": 42,
   "ignore_user_permissions": 0,
   "ignore_xss_filter": 0,
   "in_global_search": 0,
   "in_list_view": 0,
   "in_standard_filter": 0,
   "insert_after": "conversion_rate",
   "label": "Exchange Rate IDR",
   "modified": "2019-08-17 22:18:15.119926",
   "modified_by": "Administrator",
   "name": "Delivery Note-exchange_rate_idr",
   "no_copy": 0,
   "options": null,
   "owner": "Administrator",
   "parent": null,
   "parentfield": null,
   "parenttype": null,
   "permlevel": 0,
   "precision": "",
   "print_hide": 0,
   "print_hide_if_no_value": 0,
   "print_width": null,
   "read_only": 0,
   "report_hide": 0,
   "reqd": 0,
   "search_index": 0,
   "translatable": 1,
   "unique": 0,
   "width": null
  }
 ],
 "custom_perms": [
  {
   "_assign": null,
   "_comments": null,
   "_liked_by": null,
   "_user_tags": null,
   "amend": 0,
   "cancel": 0,
   "create": 0,
   "creation": "2013-05-24 19:29:09",
   "delete": 0,
   "docstatus": 0,
   "email": 0,
   "export": 0,
   "idx": 5,
   "if_owner": 0,
   "import": 0,
   "modified": "2019-08-20 10:30:51.814377",
   "modified_by": "Administrator",
   "name": "75edb77e99",
   "owner": "Administrator",
   "parent": "Delivery Note",
   "parentfield": "permissions",
   "parenttype": "DocType",
   "permlevel": 1,
   "print": 0,
   "read": 1,
   "report": 0,
   "role": "Stock Manager",
   "set_user_permissions": 0,
   "share": 0,
   "submit": 0,
   "write": 1
  },
  {
   "_assign": null,
   "_comments": null,
   "_liked_by": null,
   "_user_tags": null,
   "amend": 1,
   "cancel": 1,
   "create": 1,
   "creation": "2013-05-24 19:29:09",
   "delete": 1,
   "docstatus": 0,
   "email": 1,
   "export": 0,
   "idx": 2,
   "if_owner": 0,
   "import": 0,
   "modified": "2019-08-20 10:30:51.846839",
   "modified_by": "Administrator",
   "name": "9254059549",
   "owner": "Administrator",
   "parent": "Delivery Note",
   "parentfield": "permissions",
   "parenttype": "DocType",
   "permlevel": 0,
   "print": 1,
   "read": 1,
   "report": 1,
   "role": "Stock Manager",
   "set_user_permissions": 0,
   "share": 1,
   "submit": 1,
   "write": 1
  },
  {
   "_assign": null,
   "_comments": null,
   "_liked_by": null,
   "_user_tags": null,
   "amend": 0,
   "cancel": 0,
   "create": 0,
   "creation": "2013-05-24 19:29:09",
   "delete": 0,
   "docstatus": 0,
   "email": 0,
   "export": 0,
   "idx": 4,
   "if_owner": 0,
   "import": 0,
   "modified": "2019-08-20 10:30:51.858878",
   "modified_by": "Administrator",
   "name": "7fb8fd1f0f",
   "owner": "Administrator",
   "parent": "Delivery Note",
   "parentfield": "permissions",
   "parenttype": "DocType",
   "permlevel": 0,
   "print": 0,
   "read": 1,
   "report": 1,
   "role": "Accounts User",
   "set_user_permissions": 0,
   "share": 0,
   "submit": 0,
   "write": 0
  },
  {
   "_assign": null,
   "_comments": null,
   "_liked_by": null,
   "_user_tags": null,
   "amend": 1,
   "cancel": 1,
   "create": 1,
   "creation": "2013-05-24 19:29:09",
   "delete": 1,
   "docstatus": 0,
   "email": 1,
   "export": 0,
   "idx": 1,
   "if_owner": 0,
   "import": 0,
   "modified": "2019-08-20 10:30:51.870981",
   "modified_by": "Administrator",
   "name": "fd9f17bc53",
   "owner": "Administrator",
   "parent": "Delivery Note",
   "parentfield": "permissions",
   "parenttype": "DocType",
   "permlevel": 0,
   "print": 1,
   "read": 1,
   "report": 1,
   "role": "Stock User",
   "set_user_permissions": 0,
   "share": 1,
   "submit": 1,
   "write": 1
  },
  {
   "_assign": null,
   "_comments": null,
   "_liked_by": null,
   "_user_tags": null,
   "amend": 1,
   "cancel": 1,
   "create": 1,
   "creation": "2013-05-24 19:29:09",
   "delete": 1,
   "docstatus": 0,
   "email": 1,
   "export": 0,
   "idx": 3,
   "if_owner": 0,
   "import": 0,
   "modified": "2019-08-20 10:30:51.883491",
   "modified_by": "Administrator",
   "name": "7f3c8d55af",
   "owner": "Administrator",
   "parent": "Delivery Note",
   "parentfield": "permissions",
   "parenttype": "DocType",
   "permlevel": 0,
   "print": 1,
   "read": 1,
   "report": 1,
   "role": "Sales User",
   "set_user_permissions": 0,
   "share": 1,
   "submit": 1,
   "write": 1
  },
  {
   "_assign": null,
   "_comments": null,
   "_liked_by": null,
   "_user_tags": null,
   "amend": 1,
   "cancel": 1,
   "create": 1,
   "creation": "2019-08-20 10:30:51.900870",
   "delete": 0,
   "docstatus": 0,
   "email": 0,
   "export": 1,
   "idx": 0,
   "if_owner": 0,
   "import": 0,
   "modified": "2019-08-20 10:30:51.900870",
   "modified_by": "Administrator",
   "name": "bb87006cd7",
   "owner": "Administrator",
   "parent": "Delivery Note",
   "parentfield": "permissions",
   "parenttype": "DocType",
   "permlevel": 0,
   "print": 1,
   "read": 1,
   "report": 1,
   "role": "Bagian Delivery",
   "set_user_permissions": 0,
   "share": 0,
   "submit": 1,
   "write": 1
  },
  {
   "_assign": null,
   "_comments": null,
   "_liked_by": null,
   "_user_tags": null,
   "amend": 0,
   "cancel": 0,
   "create": 0,
   "creation": "2019-08-20 10:54:17.627780",
   "delete": 0,
   "docstatus": 0,
   "email": 0,
   "export": 1,
   "idx": 0,
   "if_owner": 0,
   "import": 0,
   "modified": "2019-08-20 10:54:17.627780",
   "modified_by": "Administrator",
   "name": "f15be1f375",
   "owner": "Administrator",
   "parent": "Delivery Note",
   "parentfield": "permissions",
   "parenttype": "DocType",
   "permlevel": 0,
   "print": 0,
   "read": 1,
   "report": 0,
   "role": "Bagian Sales Invoice",
   "set_user_permissions": 0,
   "share": 0,
   "submit": 0,
   "write": 0
  },
  {
   "_assign": null,
   "_comments": null,
   "_liked_by": null,
   "_user_tags": null,
   "amend": 1,
   "cancel": 1,
   "create": 1,
   "creation": "2019-09-18 16:28:16.730028",
   "delete": 0,
   "docstatus": 0,
   "email": 0,
   "export": 1,
   "idx": 0,
   "if_owner": 0,
   "import": 0,
   "modified": "2019-09-18 16:28:16.730028",
   "modified_by": "Administrator",
   "name": "9ba0322c5d",
   "owner": "Administrator",
   "parent": "Delivery Note",
   "parentfield": "permissions",
   "parenttype": "DocType",
   "permlevel": 0,
   "print": 0,
   "read": 1,
   "report": 1,
   "role": "Bagian Akunting",
   "set_user_permissions": 0,
   "share": 0,
   "submit": 1,
   "write": 1
  }
 ],
 "doctype": "Delivery Note",
 "property_setters": [
  {
   "_assign": null,
   "_comments": null,
   "_liked_by": null,
   "_user_tags": null,
   "creation": "2019-09-22 15:06:57.395834",
   "default_value": null,
   "doc_type": "Delivery Note",
   "docstatus": 0,
   "doctype_or_field": "DocType",
   "field_name": null,
   "idx": 0,
   "modified": "2019-09-22 15:06:57.395834",
   "modified_by": "Administrator",
   "name": "Delivery Note-read_only_onload",
   "owner": "Administrator",
   "parent": null,
   "parentfield": null,
   "parenttype": null,
   "property": "read_only_onload",
   "property_type": "Check",
   "value": null
  },
  {
   "_assign": null,
   "_comments": null,
   "_liked_by": null,
   "_user_tags": null,
   "creation": "2019-09-22 15:06:09.727650",
   "default_value": null,
   "doc_type": "Delivery Note",
   "docstatus": 0,
   "doctype_or_field": "DocField",
   "field_name": "scan_barcode",
   "idx": 0,
   "modified": "2019-09-22 15:06:09.727650",
   "modified_by": "Administrator",
   "name": "Delivery Note-scan_barcode-hidden",
   "owner": "Administrator",
   "parent": null,
   "parentfield": null,
   "parenttype": null,
   "property": "hidden",
   "property_type": "Check",
   "value": "1"
  },
  {
   "_assign": null,
   "_comments": null,
   "_liked_by": null,
   "_user_tags": null,
   "creation": "2019-08-22 12:03:17.526112",
   "default_value": null,
   "doc_type": "Delivery Note",
   "docstatus": 0,
   "doctype_or_field": "DocField",
   "field_name": "naming_series",
   "idx": 0,
   "modified": "2019-08-28 13:40:28.621321",
   "modified_by": "Administrator",
   "name": "Delivery Note-naming_series-default",
   "owner": "Administrator",
   "parent": null,
   "parentfield": null,
   "parenttype": null,
   "property": "default",
   "property_type": "Text",
   "value": "IDK-SJ-.MM./.YYYY./"
  },
  {
   "_assign": null,
   "_comments": null,
   "_liked_by": null,
   "_user_tags": null,
   "creation": "2019-08-22 12:03:17.507323",
   "default_value": null,
   "doc_type": "Delivery Note",
   "docstatus": 0,
   "doctype_or_field": "DocField",
   "field_name": "naming_series",
   "idx": 0,
   "modified": "2019-08-28 13:40:28.565446",
   "modified_by": "Administrator",
   "name": "Delivery Note-naming_series-options",
   "owner": "Administrator",
   "parent": null,
   "parentfield": null,
   "parenttype": null,
   "property": "options",
   "property_type": "Text",
   "value": "IDK-SJ-.MM./.YYYY./"
  },
  {
   "_assign": null,
   "_comments": null,
   "_liked_by": null,
   "_user_tags": null,
   "creation": "2019-08-22 13:10:46.607213",
   "default_value": null,
   "doc_type": "Delivery Note",
   "docstatus": 0,
   "doctype_or_field": "DocType",
   "field_name": null,
   "idx": 0,
   "modified": "2019-08-22 13:10:46.607213",
   "modified_by": "Administrator",
   "name": "Delivery Note-default_print_format",
   "owner": "Administrator",
   "parent": null,
   "parentfield": null,
   "parenttype": null,
   "property": "default_print_format",
   "property_type": "Data",
   "value": "INDAEKO_DeliveryNoteReport"
  },
  {
   "_assign": null,
   "_comments": null,
   "_liked_by": null,
   "_user_tags": null,
   "creation": "2019-08-17 22:23:22.917392",
   "default_value": null,
   "doc_type": "Delivery Note",
   "docstatus": 0,
   "doctype_or_field": "DocField",
   "field_name": "section_break1",
   "idx": 0,
   "modified": "2019-08-17 22:23:22.917392",
   "modified_by": "Administrator",
   "name": "Delivery Note-section_break1-hidden",
   "owner": "Administrator",
   "parent": null,
   "parentfield": null,
   "parenttype": null,
   "property": "hidden",
   "property_type": "Check",
   "value": "1"
  },
  {
   "_assign": null,
   "_comments": null,
   "_liked_by": null,
   "_user_tags": null,
   "creation": "2019-08-17 22:23:22.911847",
   "default_value": null,
   "doc_type": "Delivery Note",
   "docstatus": 0,
   "doctype_or_field": "DocField",
   "field_name": "sales_team_section_break",
   "idx": 0,
   "modified": "2019-08-17 22:23:22.911847",
   "modified_by": "Administrator",
   "name": "Delivery Note-sales_team_section_break-hidden",
   "owner": "Administrator",
   "parent": null,
   "parentfield": null,
   "parenttype": null,
   "property": "hidden",
   "property_type": "Check",
   "value": "1"
  },
  {
   "_assign": null,
   "_comments": null,
   "_liked_by": null,
   "_user_tags": null,
   "creation": "2019-08-17 22:22:19.800634",
   "default_value": null,
   "doc_type": "Delivery Note",
   "docstatus": 0,
   "doctype_or_field": "DocField",
   "field_name": "more_info",
   "idx": 0,
   "modified": "2019-08-17 22:22:19.800634",
   "modified_by": "Administrator",
   "name": "Delivery Note-more_info-hidden",
   "owner": "Administrator",
   "parent": null,
   "parentfield": null,
   "parenttype": null,
   "property": "hidden",
   "property_type": "Check",
   "value": "1"
  },
  {
   "_assign": null,
   "_comments": null,
   "_liked_by": null,
   "_user_tags": null,
   "creation": "2019-08-17 22:21:25.212078",
   "default_value": null,
   "doc_type": "Delivery Note",
   "docstatus": 0,
   "doctype_or_field": "DocField",
   "field_name": "shipping_rule",
   "idx": 0,
   "modified": "2019-08-17 22:21:25.212078",
   "modified_by": "Administrator",
   "name": "Delivery Note-shipping_rule-hidden",
   "owner": "Administrator",
   "parent": null,
   "parentfield": null,
   "parenttype": null,
   "property": "hidden",
   "property_type": "Check",
   "value": "1"
  },
  {
   "_assign": null,
   "_comments": null,
   "_liked_by": null,
   "_user_tags": null,
   "creation": "2019-08-17 22:19:21.888789",
   "default_value": null,
   "doc_type": "Delivery Note",
   "docstatus": 0,
   "doctype_or_field": "DocField",
   "field_name": "to_warehouse",
   "idx": 0,
   "modified": "2019-08-17 22:19:21.888789",
   "modified_by": "Administrator",
   "name": "Delivery Note-to_warehouse-hidden",
   "owner": "Administrator",
   "parent": null,
   "parentfield": null,
   "parenttype": null,
   "property": "hidden",
   "property_type": "Check",
   "value": "1"
  },
  {
   "_assign": null,
   "_comments": null,
   "_liked_by": null,
   "_user_tags": null,
   "creation": "2019-08-17 22:17:10.785927",
   "default_value": null,
   "doc_type": "Delivery Note",
   "docstatus": 0,
   "doctype_or_field": "DocField",
   "field_name": "customer_po_details",
   "idx": 0,
   "modified": "2019-08-17 22:17:10.785927",
   "modified_by": "Administrator",
   "name": "Delivery Note-customer_po_details-hidden",
   "owner": "Administrator",
   "parent": null,
   "parentfield": null,
   "parenttype": null,
   "property": "hidden",
   "property_type": "Check",
   "value": "1"
  },
  {
   "_assign": null,
   "_comments": null,
   "_liked_by": null,
   "_user_tags": null,
   "creation": "2019-09-20 10:51:52.445406",
   "default_value": null,
   "doc_type": "Delivery Note",
   "docstatus": 0,
   "doctype_or_field": "DocField",
   "field_name": "in_words",
   "idx": 0,
   "modified": "2019-05-08 10:00:37.573419",
   "modified_by": "Administrator",
   "name": "Delivery Note-in_words-print_hide",
   "owner": "Administrator",
   "parent": null,
   "parentfield": null,
   "parenttype": null,
   "property": "print_hide",
   "property_type": "Check",
   "value": "0"
  },
  {
   "_assign": null,
   "_comments": null,
   "_liked_by": null,
   "_user_tags": null,
   "creation": "2019-09-20 10:51:52.422979",
   "default_value": null,
   "doc_type": "Delivery Note",
   "docstatus": 0,
   "doctype_or_field": "DocField",
   "field_name": "in_words",
   "idx": 0,
   "modified": "2019-05-08 10:00:37.448224",
   "modified_by": "Administrator",
   "name": "Delivery Note-in_words-hidden",
   "owner": "Administrator",
   "parent": null,
   "parentfield": null,
   "parenttype": null,
   "property": "hidden",
   "property_type": "Check",
   "value": "0"
  },
  {
   "_assign": null,
   "_comments": null,
   "_liked_by": null,
   "_user_tags": null,
   "creation": "2019-09-20 10:51:52.111068",
   "default_value": null,
   "doc_type": "Delivery Note",
   "docstatus": 0,
   "doctype_or_field": "DocField",
   "field_name": "rounded_total",
   "idx": 0,
   "modified": "2019-05-08 10:00:35.686894",
   "modified_by": "Administrator",
   "name": "Delivery Note-rounded_total-print_hide",
   "owner": "Administrator",
   "parent": null,
   "parentfield": null,
   "parenttype": null,
   "property": "print_hide",
   "property_type": "Check",
   "value": "0"
  },
  {
   "_assign": null,
   "_comments": null,
   "_liked_by": null,
   "_user_tags": null,
   "creation": "2019-09-20 10:51:52.092147",
   "default_value": null,
   "doc_type": "Delivery Note",
   "docstatus": 0,
   "doctype_or_field": "DocField",
   "field_name": "rounded_total",
   "idx": 0,
   "modified": "2019-05-08 10:00:35.561215",
   "modified_by": "Administrator",
   "name": "Delivery Note-rounded_total-hidden",
   "owner": "Administrator",
   "parent": null,
   "parentfield": null,
   "parenttype": null,
   "property": "hidden",
   "property_type": "Check",
   "value": "0"
  },
  {
   "_assign": null,
   "_comments": null,
   "_liked_by": null,
   "_user_tags": null,
   "creation": "2019-09-20 10:51:52.073612",
   "default_value": null,
   "doc_type": "Delivery Note",
   "docstatus": 0,
   "doctype_or_field": "DocField",
   "field_name": "base_rounded_total",
   "idx": 0,
   "modified": "2019-05-08 10:00:35.438314",
   "modified_by": "Administrator",
   "name": "Delivery Note-base_rounded_total-print_hide",
   "owner": "Administrator",
   "parent": null,
   "parentfield": null,
   "parenttype": null,
   "property": "print_hide",
   "property_type": "Check",
   "value": "1"
  },
  {
   "_assign": null,
   "_comments": null,
   "_liked_by": null,
   "_user_tags": null,
   "creation": "2019-09-20 10:51:52.056042",
   "default_value": null,
   "doc_type": "Delivery Note",
   "docstatus": 0,
   "doctype_or_field": "DocField",
   "field_name": "base_rounded_total",
   "idx": 0,
   "modified": "2019-05-08 10:00:35.315691",
   "modified_by": "Administrator",
   "name": "Delivery Note-base_rounded_total-hidden",
   "owner": "Administrator",
   "parent": null,
   "parentfield": null,
   "parenttype": null,
   "property": "hidden",
   "property_type": "Check",
   "value": "0"
  },
  {
   "_assign": null,
   "_comments": null,
   "_liked_by": null,
   "_user_tags": null,
   "creation": "2019-09-20 10:51:51.783696",
   "default_value": null,
   "doc_type": "Delivery Note",
   "docstatus": 0,
   "doctype_or_field": "DocField",
   "field_name": "tax_id",
   "idx": 0,
   "modified": "2019-05-08 10:00:32.707703",
   "modified_by": "Administrator",
   "name": "Delivery Note-tax_id-print_hide",
   "owner": "Administrator",
   "parent": null,
   "parentfield": null,
   "parenttype": null,
   "property": "print_hide",
   "property_type": "Check",
   "value": "0"
  },
  {
   "_assign": null,
   "_comments": null,
   "_liked_by": null,
   "_user_tags": null,
   "creation": "2019-09-20 10:51:51.766473",
   "default_value": null,
   "doc_type": "Delivery Note",
   "docstatus": 0,
   "doctype_or_field": "DocField",
   "field_name": "tax_id",
   "idx": 0,
   "modified": "2019-05-08 10:00:32.565787",
   "modified_by": "Administrator",
   "name": "Delivery Note-tax_id-hidden",
   "owner": "Administrator",
   "parent": null,
   "parentfield": null,
   "parenttype": null,
   "property": "hidden",
   "property_type": "Check",
   "value": "0"
  }
 ],
 "sync_on_migrate": 1
}